README.md
setup.cfg
setup.py
simple_codecs/__init__.py
simple_codecs.egg-info/PKG-INFO
simple_codecs.egg-info/SOURCES.txt
simple_codecs.egg-info/dependency_links.txt
simple_codecs.egg-info/requires.txt
simple_codecs.egg-info/top_level.txt