Metadata-Version: 2.1
Name: simple-codecs
Version: 1.0
Summary: Useful tools to with encoding and encryption
Home-page: https://github.com/OsOmE1/ced
Author: OsOmE1
Author-email: 
License: MIT
Download-URL: https://pypi.org/project/simple_codecs/
Keywords: ced,Encryption,Encoding
Platform: UNKNOWN
